<?xml version="1.0" encoding="UTF-8" standalone="yes"?><ncm-object pk='9857:3725:ALT1' classversion='1.0'><pubnumber type='String'/><obj_id type='Integer'>9857</obj_id><level name='1_CURRENT' id='3.4.1.0.0' path='NP/NEWS/1_CURRENT' level='3' type='Object,HasDate'/><name type='String'>TESTJP10</name><unique_name_key type='String'>3.4.1.0.0</unique_name_key><ncm-type-property name='obj_type' type='NCMType' is-external='false' data-type='NewsRoom'><object-type name='OBJ_STORY_PACK' id='17' histories='0'><initial-status><status id='52' name='SP'/></initial-status></object-type></ncm-type-property><exp_pubdate type='Date'>27.3.2012</exp_pubdate><exp_pubdate_to type='Date'>27.3.2012</exp_pubdate_to><exp_pubdate_days type='Integer'>0</exp_pubdate_days><edition name='*****' id='0'/><purge_obj_id type='Integer'>0</purge_obj_id><is_deleted type='Boolean'>false</is_deleted><creator type='NCMUser'><id>5</id><name>MARIANOJP</name><type>SYSADMIN</type></creator><creation_ts type='Date'>28.3.2012</creation_ts><modifier type='NCMUser'><id>5</id><name>MARIANOJP</name><type>SYSADMIN</type></modifier><modifier_ts type='Date'>28.3.2012</modifier_ts><modifier_ws type='Integer'>1138</modifier_ws><modifying type='NCMUser'/><modifying_ws type='Integer'>0</modifying_ws><modifying_app type='Short'>0</modifying_app><is_locked type='Boolean'>false</is_locked><lock_type type='Short'>0</lock_type><hermes_version type='Integer'>0</hermes_version><storage_format type='Integer'>0</storage_format><priority type='Integer'>0</priority><author type='String'>MARIANOJP</author><real_chars type='Integer'>0</real_chars><parent_id type='Integer'>0</parent_id><department_id type='Integer'>1</department_id><last_update_ts type='Date'>28.3.2012</last_update_ts><property name='retention_time' type='Integer'>0</property><version type='Integer'>0</version><content_version type='Integer'>0</content_version><content_modifier type='NCMUser'><id>5</id><name>MARIANOJP</name><type>SYSADMIN</type></content_modifier><content_modifier_ts type='Date'>28.3.2012</content_modifier_ts><copy_obj_id type='Integer'>0</copy_obj_id><copy_obj_mode type='Integer'>0</copy_obj_mode><variant_of_obj_id type='Integer'>0</variant_of_obj_id><variant_type name='' id='0'/><numb_of_variants type='Integer'>0</numb_of_variants><relation_obj_id type='Integer'>0</relation_obj_id><sp_id type='Integer'>0</sp_id><numb_of_sp_objs type='Integer'>4</numb_of_sp_objs><relation_type type='Integer'>0</relation_type><exp_page_number type='Integer'>0</exp_page_number><n_links type='Integer'>1</n_links><template_id type='Integer'>0</template_id><data_type type='String'>NewsRoom</data_type><var_group_last_update type='NCMLastUpdatedVariant'><last-obj-id type='Integer'>9857</last-obj-id><last-obj-name type='String'>TESTJP10</last-obj-name><last-obj-upd-relevance type='Short'>0</last-obj-upd-relevance><last-content-modifier-ts type='Date'>28.3.2012</last-content-modifier-ts><last-content-modifier type='NCMUser'><id>5</id><name>MARIANOJP</name><type>SYSADMIN</type></last-content-modifier><variant_type name='' id='0'/></var_group_last_update><init_obj_mode type='Integer'>0</init_obj_mode><ncm-attachment-property name='attachments' type='NCMAttachment' count='0'/><upd_relevance type='Short'>0</upd_relevance><flags type='Integer'>0</flags><orig_obj_id type='Integer'>0</orig_obj_id><size_graphical_file type='Long'>-1</size_graphical_file><size_native_file type='Long'>-1</size_native_file><property name='copy_infos' type='NCMCopyInfo'>0-0-0-0-0-0</property><mediatype type='String'>ncm-object-17-NewsRoom</mediatype><child_pks type='PkVector' count='4'><ncm-object-pk classversion='1.0'><object-id>9863</object-id><layout-id>unknown</layout-id></ncm-object-pk><ncm-object-pk classversion='1.0'><object-id>9860</object-id><layout-id>unknown</layout-id></ncm-object-pk><ncm-object-pk classversion='1.0'><object-id>9859</object-id><layout-id>unknown</layout-id></ncm-object-pk><ncm-object-pk classversion='1.0'><object-id>9858</object-id><layout-id>unknown</layout-id></ncm-object-pk></child_pks><is_object_link type='Boolean'>false</is_object_link><allowed_pagination type='Boolean'>true</allowed_pagination><extra-properties/><child-of-a-ncm-sp-object count='4'><ncm-object pk='9858:3723:ALT1' classversion='1.0'><pubnumber type='String'/><obj_id type='Integer'>9858</obj_id><level name='1_CURRENT' id='3.4.1.0.0' path='NP/NEWS/1_CURRENT' level='3' type='Object,HasDate'/><name type='String'>TESTJP10-A</name><unique_name_key type='String'>3.4.1.0.0</unique_name_key><ncm-type-property name='obj_type' type='NCMType' is-external='false' data-type='NewsRoom'><object-type name='OBJ_TXT' id='1' histories='50'><initial-status><status id='9' name='STORY_NEW'/></initial-status></object-type></ncm-type-property><exp_pubdate type='Date'>27.3.2012</exp_pubdate><exp_pubdate_days type='Integer'>0</exp_pubdate_days><edition name='*****' id='0'/><purge_obj_id type='Integer'>0</purge_obj_id><is_deleted type='Boolean'>false</is_deleted><creator type='NCMUser'><id>5</id><name>MARIANOJP</name><type>SYSADMIN</type></creator><creation_ts type='Date'>28.3.2012</creation_ts><modifier type='NCMUser'><id>5</id><name>MARIANOJP</name><type>SYSADMIN</type></modifier><modifier_ts type='Date'>28.3.2012</modifier_ts><modifier_ws type='Integer'>1138</modifier_ws><modifying type='NCMUser'/><modifying_ws type='Integer'>0</modifying_ws><modifying_app type='Short'>0</modifying_app><is_locked type='Boolean'>false</is_locked><lock_type type='Short'>0</lock_type><hermes_version type='Integer'>0</hermes_version><storage_format type='Integer'>0</storage_format><priority type='Integer'>0</priority><real_chars type='Integer'>1293</real_chars><effectivecolors type='NCMColor'><stdcolors type='String'>K</stdcolors><options type='String'>SEPARATION 4PLATES</options></effectivecolors><text_preview type='String'>hello world!! This section explains the various elements available in the NewsRoom layout mode. For each element, a description of all available configuration parameters is provided, along with an explanation of how to use them within the NewsRoom lay </text_preview><parent_id type='Integer'>0</parent_id><department_id type='Integer'>1</department_id><last_update_ts type='Date'>28.3.2012</last_update_ts><property name='retention_time' type='Integer'>0</property><version type='Integer'>0</version><content_version type='Integer'>0</content_version><content_modifier type='NCMUser'><id>5</id><name>MARIANOJP</name><type>SYSADMIN</type></content_modifier><content_modifier_ts type='Date'>28.3.2012</content_modifier_ts><content-property name='hermes_text' type='NCMText'><content-property name='hermes_image' type='NCMImage' imagetype='TIFF'><file-property name='hermes_image' type='NCMImage'><file-name>OBJ9858_4.JPG</file-name><original-file href='http://H11LNXVM:8080/ncm/dispatcher?auth=U0VTU0lPTklENDE2NTcxMDgyOjQxNjU3MTA4Mg==&amp;url=/ncm/file?file=/hedata/archive/extObj/NewsRoom/1/3/4/1/20120327/0/OBJ9858_4.JPG'><server-path>/hedata/archive/extObj/NewsRoom/1/3/4/1/20120327/0/OBJ9858_4.JPG</server-path></original-file><medium-preview href='http://H11LNXVM:8080/ncm/dispatcher?auth=U0VTU0lPTklENDE2NTcxMDgyOjQxNjU3MTA4Mg==&amp;url=/ncm/file?file=/hedata/archive/extObj/NewsRoom/1/3/4/1/20120327/0/OBJ9858_4.low'><server-path>/hedata/archive/extObj/NewsRoom/1/3/4/1/20120327/0/OBJ9858_4.low</server-path></medium-preview><low-preview href='http://H11LNXVM:8080/ncm/dispatcher?auth=U0VTU0lPTklENDE2NTcxMDgyOjQxNjU3MTA4Mg==&amp;url=/ncm/file?file=/hedata/archive/extObj/NewsRoom/1/3/4/1/20120327/0/OBJ9858_4.thn'><server-path>/hedata/archive/extObj/NewsRoom/1/3/4/1/20120327/0/OBJ9858_4.thn</server-path></low-preview></file-property><image-size type='NCMRect' unit='Pixel'><width>0.0</width><height>0.0</height></image-size><original-image-size type='NCMRect' unit='PSP'><width>0.0</width><height>0.0</height></original-image-size><xy-transf rotate='0.0' skew='0.0' crop-off-x='0.0' crop-off-y='0.0' norg-x='0.0' norg-y='0.0' scale-x='100.0' scale-y='100.0' dim-x='378.0' dim-y='298.0' flip-x='false' flip-y='false'/><bounding-box top='0.0' left='0.0' bottom='0.0' right='378.0'/></content-property><default-tag></default-tag><formatted>hello world!! This section explains the various elements available in the NewsRoom layout mode. For each element, a description of all available configuration parameters is provided, along with an explanation of how to use them within the NewsRoom layout mode.<uupscommand type='ep'/><uupscommand value='10' type='cs'/>Some features described later in this section may not be available to you. They may appear grayed out. If that is the case, please check if you have sufficient access rights to use these features.<uupscommand type='ep'/><uupscommand value='-30' type='cw'/>This section explains the various elements availa<uupscommand type='cs'/>ble in the NewsRoom layout mode. For each ele<uupscommand type='cw'/>ment, a description of all available configuration parameters is provided, along with an explanation of how to use them within the NewsRoom layout mode.<uupscommand type='ep'/>Some features described later in this section may not be available to you. They may appear grayed out. If that is the case, please check if you have sufficient access rights to [BRIEF]use these features.<uupscommand type='ep'/>This section explains the[/BRIEF] various elements available in the NewsRoom layout mode. For each element, a d[QUOTATION]escription of all available configuration parameters is provided, along with an explanation of how [/QUOTATION]to use them within the NewsRoom layout mode.<uupscommand type='ep'/>Some features described later in this section may not be available to you. They may appear grayed out. If that is the</formatted></content-property><copy_obj_id type='Integer'>0</copy_obj_id><copy_obj_mode type='Integer'>0</copy_obj_mode><variant_of_obj_id type='Integer'>0</variant_of_obj_id><variant_type name='' id='0'/><numb_of_variants type='Integer'>0</numb_of_variants><relation_obj_id type='Integer'>0</relation_obj_id><sp_id type='Integer'>9857</sp_id><numb_of_sp_objs type='Integer'>0</numb_of_sp_objs><relation_type type='Integer'>0</relation_type><exp_page_number type='Integer'>0</exp_page_number><n_links type='Integer'>1</n_links><template_id type='Integer'>0</template_id><data_type type='String'>NewsRoom</data_type><var_group_last_update type='NCMLastUpdatedVariant'><last-obj-id type='Integer'>9858</last-obj-id><last-obj-name type='String'>TESTJP10-A</last-obj-name><last-obj-upd-relevance type='Short'>0</last-obj-upd-relevance><last-content-modifier-ts type='Date'>28.3.2012</last-content-modifier-ts><last-content-modifier type='NCMUser'><id>5</id><name>MARIANOJP</name><type>SYSADMIN</type></last-content-modifier><variant_type name='' id='0'/></var_group_last_update><init_obj_mode type='Integer'>0</init_obj_mode><ncm-attachment-property name='attachments' type='NCMAttachment' count='0'/><upd_relevance type='Short'>0</upd_relevance><flags type='Integer'>0</flags><orig_obj_id type='Integer'>0</orig_obj_id><size_graphical_file type='Long'>-1</size_graphical_file><size_native_file type='Long'>-1</size_native_file><property name='copy_infos' type='NCMCopyInfo'>0-0-0-0-0-0</property><mediatype type='String'>ncm-object-1-NewsRoom</mediatype><is_object_link type='Boolean'>false</is_object_link><allowed_pagination type='Boolean'>true</allowed_pagination><extra-properties/><layouts-of-a-ncm-object count='1'><ncm-layout pk='9858:3723:ALT1' classversion='1.0'><dummy_obj_id type='Integer'>0</dummy_obj_id><edition name='*****' id='0'/><is_inpage type='Boolean'>true</is_inpage><obj_id type='Integer'>9858</obj_id><reference type='String'>B</reference><sub_reference type='Integer'>65</sub_reference><jump_sequence type='Integer'>0</jump_sequence><ncm-type-property name='lay_type' type='NCMType' is-external='false' data-type=''><object-type name='OBJ_TXT' id='1' histories='50'><initial-status><status id='9' name='STORY_NEW'/></initial-status></object-type></ncm-type-property><hermes_version type='Integer'>0</hermes_version><newflag type='Integer'>0</newflag><format type='String'>SP</format><surface type='Integer'>5262680</surface><agenda_id type='Integer'>0</agenda_id><assignto type='Integer'>0</assignto><obj_crc type='Integer'>-1115331653</obj_crc><obj_content type='String'>AAABAT4AAAAAAAAAAAAAAAAAAAAAAAAAAAAAAAAAAAAAAAAAAAAAAAAAAAAAAAAASEkyQgAAAQAw
AAAAYwUAAIsOAAA=</obj_content><copy_lay_mode type='Integer'>0</copy_lay_mode><init_lay_mode type='Integer'>0</init_lay_mode><version_ts type='Date'>1.1.1970</version_ts><lay_id type='Integer'>3723</lay_id><status type='NCMStatus'><status id='9' name='STORY_NEW'/><extended-status type='Integer'>2</extended-status><attribute type='Integer'>2</attribute><complex-status type='Integer'>1</complex-status><sendto type='list'><sendto>0</sendto></sendto></status><ext_status type='String'>2</ext_status><first_linked type='Boolean'>true</first_linked><edition name='FIRST' id='68' master-edition-name='*****' nm='1ST' zone-name='MAIN' time-name='FIRST'><newspaper-level level-path='NP'><level name='NP' id='3.0.0.0.0' path='NP' level='1' type='Newspaper,AllCatalogs'/></newspaper-level><page-level level-path=''><level name='ROOT' id='0.0.0.0.0' path='' level='0' type='AllCatalogs'/></page-level></edition><page_id type='Integer'>2452</page_id><sp_lay_id type='Integer'>0</sp_lay_id><page_name type='String'>NPS-003</page_name><mediatype type='String'>ncm-layout</mediatype><pub_date type='Date'>27.3.2012</pub_date><level name='PAGES' id='3.4.3.0.0' path='NP/NEWS/PAGES' level='3' type='Page,HasDate'/><property name='msendto' type='NCMMultipleSendTo'>0</property><real_size type='Integer'>4803</real_size><real_lines type='Integer'>50</real_lines><priority type='Short'>0</priority><mandatory type='Short'>0</mandatory><unique_alt_id type='Integer'>1</unique_alt_id><copy_lay_id type='Integer'>0</copy_lay_id><hermes-layout name='lay_rect' type='NCMLayBoundRect' units='PtPs'><bounding-rect xpos='0.0' ypos='287.1' width='378.9' depth='298.3' lay-lines='46'/><hermes-layout-parts><is-dummy-image type='Boolean'>true</is-dummy-image><name-template type='String'>TEST</name-template><layout-parts count='1'><layout-box subreference='65' type='1' finfo='0x401a' lock='0x0' exp-name='' style-sheet='DEFAULT'><bounding-boxes count='3'><block parent-id='9857' Units='PtPs' x='0.0' y='287.1' width='119.2' height='298.3'><rotation/><interior-color c='0' m='0' y='0' k='0'/><border-color size='0.0' c='0' m='0' y='0' k='255'/></block><blocks count='2'><block parent-id='9857' Units='PtPs' x='129.8' y='287.1' width='119.2' height='0.0'><rotation/><interior-color c='0' m='0' y='0' k='0'/><border-color size='0.0' c='0' m='0' y='0' k='0'/></block><block parent-id='9857' Units='PtPs' x='129.8' y='513.8' width='119.2' height='71.6'><rotation/><interior-color c='0' m='0' y='0' k='0'/><border-color size='0.0' c='0' m='0' y='0' k='0'/></block></blocks><block parent-id='9857' Units='PtPs' x='259.7' y='513.8' width='119.2' height='71.6'><rotation/><interior-color c='0' m='0' y='0' k='0'/><border-color size='0.0' c='0' m='0' y='0' k='0'/></block></bounding-boxes></layout-box></layout-parts></hermes-layout-parts></hermes-layout><extra-properties/></ncm-layout></layouts-of-a-ncm-object></ncm-object><ncm-object pk='9859:3722:ALT1' classversion='1.0'><pubnumber type='String'/><obj_id type='Integer'>9859</obj_id><level name='1_CURRENT' id='3.4.1.0.0' path='NP/NEWS/1_CURRENT' level='3' type='Object,HasDate'/><name type='String'>TESTJP10-B</name><unique_name_key type='String'>3.4.1.0.0</unique_name_key><ncm-type-property name='obj_type' type='NCMType' is-external='false' data-type='NewsRoom'><object-type name='OBJ_HEADLINE' id='2' histories='50'><initial-status><status id='9' name='STORY_NEW'/></initial-status></object-type></ncm-type-property><exp_pubdate type='Date'>27.3.2012</exp_pubdate><exp_pubdate_days type='Integer'>0</exp_pubdate_days><edition name='*****' id='0'/><purge_obj_id type='Integer'>0</purge_obj_id><is_deleted type='Boolean'>false</is_deleted><creator type='NCMUser'><id>5</id><name>MARIANOJP</name><type>SYSADMIN</type></creator><creation_ts type='Date'>28.3.2012</creation_ts><modifier type='NCMUser'><id>5</id><name>MARIANOJP</name><type>SYSADMIN</type></modifier><modifier_ts type='Date'>28.3.2012</modifier_ts><modifier_ws type='Integer'>1138</modifier_ws><modifying type='NCMUser'/><modifying_ws type='Integer'>0</modifying_ws><modifying_app type='Short'>0</modifying_app><is_locked type='Boolean'>false</is_locked><lock_type type='Short'>0</lock_type><hermes_version type='Integer'>0</hermes_version><storage_format type='Integer'>0</storage_format><priority type='Integer'>0</priority><real_chars type='Integer'>32</real_chars><effectivecolors type='NCMColor'><stdcolors type='String'>K</stdcolors><options type='String'>SEPARATION 4PLATES</options></effectivecolors><text_preview type='String'>this is headline1
this is line  </text_preview><parent_id type='Integer'>0</parent_id><department_id type='Integer'>1</department_id><last_update_ts type='Date'>28.3.2012</last_update_ts><property name='retention_time' type='Integer'>0</property><version type='Integer'>0</version><content_version type='Integer'>0</content_version><content_modifier type='NCMUser'><id>5</id><name>MARIANOJP</name><type>SYSADMIN</type></content_modifier><content_modifier_ts type='Date'>28.3.2012</content_modifier_ts><content-property name='hermes_header' type='NCMHeader'><content-property name='hermes_image' type='NCMImage' imagetype='TIFF'><file-property name='hermes_image' type='NCMImage'><file-name>OBJ9859_3.JPG</file-name><original-file href='http://H11LNXVM:8080/ncm/dispatcher?auth=U0VTU0lPTklENDE2NTcxMDgyOjQxNjU3MTA4Mg==&amp;url=/ncm/file?file=/hedata/archive/extObj/NewsRoom/2/3/4/1/20120327/0/OBJ9859_3.JPG'><server-path>/hedata/archive/extObj/NewsRoom/2/3/4/1/20120327/0/OBJ9859_3.JPG</server-path></original-file><medium-preview href='http://H11LNXVM:8080/ncm/dispatcher?auth=U0VTU0lPTklENDE2NTcxMDgyOjQxNjU3MTA4Mg==&amp;url=/ncm/file?file=/hedata/archive/extObj/NewsRoom/2/3/4/1/20120327/0/OBJ9859_3.low'><server-path>/hedata/archive/extObj/NewsRoom/2/3/4/1/20120327/0/OBJ9859_3.low</server-path></medium-preview><low-preview href='http://H11LNXVM:8080/ncm/dispatcher?auth=U0VTU0lPTklENDE2NTcxMDgyOjQxNjU3MTA4Mg==&amp;url=/ncm/file?file=/hedata/archive/extObj/NewsRoom/2/3/4/1/20120327/0/OBJ9859_3.thn'><server-path>/hedata/archive/extObj/NewsRoom/2/3/4/1/20120327/0/OBJ9859_3.thn</server-path></low-preview></file-property><image-size type='NCMRect' unit='Pixel'><width>0.0</width><height>0.0</height></image-size><original-image-size type='NCMRect' unit='PSP'><width>0.0</width><height>0.0</height></original-image-size><xy-transf rotate='0.0' skew='0.0' crop-off-x='0.0' crop-off-y='0.0' norg-x='0.0' norg-y='0.0' scale-x='100.0' scale-y='100.0' dim-x='380.0' dim-y='74.0' flip-x='false' flip-y='false'/><bounding-box top='0.0' left='0.0' bottom='0.0' right='380.0'/></content-property><content-property name='hermes_text' type='NCMText' sub-type='Maintitle'><formatted>this is headline1<uupscommand type='ep'/>this is line 2</formatted></content-property></content-property><copy_obj_id type='Integer'>0</copy_obj_id><copy_obj_mode type='Integer'>0</copy_obj_mode><variant_of_obj_id type='Integer'>0</variant_of_obj_id><variant_type name='' id='0'/><numb_of_variants type='Integer'>1</numb_of_variants><relation_obj_id type='Integer'>0</relation_obj_id><sp_id type='Integer'>9857</sp_id><numb_of_sp_objs type='Integer'>0</numb_of_sp_objs><relation_type type='Integer'>0</relation_type><exp_page_number type='Integer'>0</exp_page_number><n_links type='Integer'>1</n_links><template_id type='Integer'>0</template_id><data_type type='String'>NewsRoom</data_type><var_group_last_update type='NCMLastUpdatedVariant'><last-obj-id type='Integer'>9863</last-obj-id><last-obj-name type='String'>TESTJP10-B_PRINT</last-obj-name><last-obj-upd-relevance type='Short'>0</last-obj-upd-relevance><last-content-modifier-ts type='Date'>28.3.2012</last-content-modifier-ts><last-content-modifier type='NCMUser'><id>5</id><name>MARIANOJP</name><type>SYSADMIN</type></last-content-modifier><variant_type name='PRINT' id='4098'/></var_group_last_update><init_obj_mode type='Integer'>0</init_obj_mode><ncm-attachment-property name='attachments' type='NCMAttachment' count='0'/><upd_relevance type='Short'>0</upd_relevance><flags type='Integer'>0</flags><orig_obj_id type='Integer'>0</orig_obj_id><size_graphical_file type='Long'>-1</size_graphical_file><size_native_file type='Long'>-1</size_native_file><property name='copy_infos' type='NCMCopyInfo'>0-0-0-0-0-0</property><mediatype type='String'>ncm-object-2-NewsRoom</mediatype><is_object_link type='Boolean'>false</is_object_link><allowed_pagination type='Boolean'>true</allowed_pagination><extra-properties/><layouts-of-a-ncm-object count='1'><ncm-layout pk='9859:3722:ALT1' classversion='1.0'><dummy_obj_id type='Integer'>0</dummy_obj_id><edition name='FIRST' id='68' master-edition-name='*****' nm='1ST' zone-name='MAIN' time-name='FIRST'><newspaper-level level-path='NP'><level name='NP' id='3.0.0.0.0' path='NP' level='1' type='Newspaper,AllCatalogs'/></newspaper-level><page-level level-path=''><level name='ROOT' id='0.0.0.0.0' path='' level='0' type='AllCatalogs'/></page-level></edition><is_inpage type='Boolean'>true</is_inpage><obj_id type='Integer'>9859</obj_id><reference type='String'>TESTJP10-B</reference><sub_reference type='Integer'>66</sub_reference><jump_sequence type='Integer'>0</jump_sequence><ncm-type-property name='lay_type' type='NCMType' is-external='false' data-type=''><object-type name='OBJ_HEADLINE' id='2' histories='50'><initial-status><status id='9' name='STORY_NEW'/></initial-status></object-type></ncm-type-property><hermes_version type='Integer'>0</hermes_version><newflag type='Integer'>0</newflag><format type='String'>34-2LIGNE</format><surface type='Integer'>2844644</surface><agenda_id type='Integer'>0</agenda_id><assignto type='Integer'>0</assignto><obj_crc type='Integer'>142281288</obj_crc><obj_content type='String'>AAACASYAAAAAAAAAAAAAAAAAAAAAAAAASEkyQgABAQAwAAAAVQAAAIoOAAA=</obj_content><copy_lay_mode type='Integer'>0</copy_lay_mode><init_lay_mode type='Integer'>0</init_lay_mode><version_ts type='Date'>1.1.1970</version_ts><lay_id type='Integer'>3722</lay_id><status type='NCMStatus'><status id='9' name='STORY_NEW'/><extended-status type='Integer'>1</extended-status><attribute type='Integer'>3</attribute><complex-status type='Integer'>1</complex-status><sendto type='list'><sendto>0</sendto></sendto></status><ext_status type='String'>1</ext_status><first_linked type='Boolean'>true</first_linked><edition name='FIRST' id='68' master-edition-name='*****' nm='1ST' zone-name='MAIN' time-name='FIRST'><newspaper-level level-path='NP'><level name='NP' id='3.0.0.0.0' path='NP' level='1' type='Newspaper,AllCatalogs'/></newspaper-level><page-level level-path=''><level name='ROOT' id='0.0.0.0.0' path='' level='0' type='AllCatalogs'/></page-level></edition><page_id type='Integer'>2452</page_id><sp_lay_id type='Integer'>0</sp_lay_id><page_name type='String'>NPS-003</page_name><mediatype type='String'>ncm-layout</mediatype><pub_date type='Date'>27.3.2012</pub_date><level name='PAGES' id='3.4.3.0.0' path='NP/NEWS/PAGES' level='3' type='Page,HasDate'/><property name='msendto' type='NCMMultipleSendTo'>0</property><real_size type='Integer'>714</real_size><real_lines type='Integer'>2</real_lines><priority type='Short'>0</priority><mandatory type='Short'>0</mandatory><unique_alt_id type='Integer'>1</unique_alt_id><copy_lay_id type='Integer'>0</copy_lay_id><hermes-layout name='lay_rect' type='NCMLayBoundRect' units='PtPs'><bounding-rect xpos='0.0' ypos='207.8' width='380.3' depth='74.8' lay-lines='2'/><hermes-layout-parts><is-dummy-image type='Boolean'>true</is-dummy-image><name-template type='String'>SP</name-template><layout-parts count='1'><layout-box subreference='66' type='2' finfo='0x4012' lock='0x0' exp-name='' style-sheet='Titre'><bounding-boxes count='1'><block parent-id='9857' Units='PtPs' x='0.0' y='207.8' width='380.3' height='74.8'><rotation/><interior-color c='0' m='0' y='0' k='0'/><border-color size='0.0' c='0' m='0' y='0' k='255'/></block></bounding-boxes></layout-box></layout-parts></hermes-layout-parts></hermes-layout><extra-properties/></ncm-layout></layouts-of-a-ncm-object><variants-of-a-ncm-object count='1'><ncm-object pk='9863:0' classversion='1.0'><pubnumber type='String'/><obj_id type='Integer'>9863</obj_id><level name='1_CURRENT' id='3.4.1.0.0' path='NP/NEWS/1_CURRENT' level='3' type='Object,HasDate'/><name type='String'>TESTJP10-B_PRINT</name><unique_name_key type='String'>3.4.1.0.0</unique_name_key><ncm-type-property name='obj_type' type='NCMType' is-external='false' data-type='NewsRoom'><object-type name='OBJ_HEADLINE' id='2' histories='50'><initial-status><status id='9' name='STORY_NEW'/></initial-status></object-type></ncm-type-property><exp_pubdate type='Date'>27.3.2012</exp_pubdate><exp_pubdate_days type='Integer'>0</exp_pubdate_days><edition name='FIRST' id='68' master-edition-name='*****' nm='1ST' zone-name='MAIN' time-name='FIRST'><newspaper-level level-path='NP'><level name='NP' id='3.0.0.0.0' path='NP' level='1' type='Newspaper,AllCatalogs'/></newspaper-level><page-level level-path=''><level name='ROOT' id='0.0.0.0.0' path='' level='0' type='AllCatalogs'/></page-level></edition><purge_obj_id type='Integer'>0</purge_obj_id><is_deleted type='Boolean'>false</is_deleted><creator type='NCMUser'><id>5</id><name>MARIANOJP</name><type>SYSADMIN</type></creator><creation_ts type='Date'>28.3.2012</creation_ts><modifier type='NCMUser'><id>5</id><name>MARIANOJP</name><type>SYSADMIN</type></modifier><modifier_ts type='Date'>28.3.2012</modifier_ts><modifier_ws type='Integer'>1138</modifier_ws><modifying type='NCMUser'/><modifying_ws type='Integer'>0</modifying_ws><modifying_app type='Short'>0</modifying_app><is_locked type='Boolean'>false</is_locked><lock_type type='Short'>0</lock_type><hermes_version type='Integer'>0</hermes_version><storage_format type='Integer'>0</storage_format><priority type='Integer'>0</priority><author type='String'>MARIANOJP</author><real_chars type='Integer'>32</real_chars><effectivecolors type='NCMColor'><stdcolors type='String'>K</stdcolors><options type='String'>SEPARATION 4PLATES</options></effectivecolors><text_preview type='String'>this is headline1
this is line  </text_preview><parent_id type='Integer'>0</parent_id><department_id type='Integer'>1</department_id><last_update_ts type='Date'>28.3.2012</last_update_ts><property name='retention_time' type='Integer'>0</property><version type='Integer'>0</version><content_version type='Integer'>0</content_version><content_modifier type='NCMUser'><id>5</id><name>MARIANOJP</name><type>SYSADMIN</type></content_modifier><content_modifier_ts type='Date'>28.3.2012</content_modifier_ts><content-property name='hermes_header' type='NCMHeader'><content-property name='hermes_image' type='NCMImage' imagetype='TIFF'><file-property name='hermes_image' type='NCMImage'><file-name>OBJ9863_5.JPG</file-name><original-file href='http://H11LNXVM:8080/ncm/dispatcher?auth=U0VTU0lPTklENDE2NTcxMDgyOjQxNjU3MTA4Mg==&amp;url=/ncm/file?file=/hedata/archive/extObj/NewsRoom/2/3/4/1/20120327/68/OBJ9863_5.JPG'><server-path>/hedata/archive/extObj/NewsRoom/2/3/4/1/20120327/68/OBJ9863_5.JPG</server-path></original-file><medium-preview href='http://H11LNXVM:8080/ncm/dispatcher?auth=U0VTU0lPTklENDE2NTcxMDgyOjQxNjU3MTA4Mg==&amp;url=/ncm/file?file=/hedata/archive/extObj/NewsRoom/2/3/4/1/20120327/68/OBJ9863_5.low'><server-path>/hedata/archive/extObj/NewsRoom/2/3/4/1/20120327/68/OBJ9863_5.low</server-path></medium-preview><low-preview href='http://H11LNXVM:8080/ncm/dispatcher?auth=U0VTU0lPTklENDE2NTcxMDgyOjQxNjU3MTA4Mg==&amp;url=/ncm/file?file=/hedata/archive/extObj/NewsRoom/2/3/4/1/20120327/68/OBJ9863_5.thn'><server-path>/hedata/archive/extObj/NewsRoom/2/3/4/1/20120327/68/OBJ9863_5.thn</server-path></low-preview></file-property><image-size type='NCMRect' unit='Pixel'><width>0.0</width><height>0.0</height></image-size><original-image-size type='NCMRect' unit='PSP'><width>0.0</width><height>0.0</height></original-image-size><xy-transf rotate='0.0' skew='0.0' crop-off-x='0.0' crop-off-y='0.0' norg-x='0.0' norg-y='0.0' scale-x='100.0' scale-y='100.0' dim-x='380.0' dim-y='74.0' flip-x='false' flip-y='false'/><bounding-box top='0.0' left='0.0' bottom='0.0' right='380.0'/></content-property><content-property name='hermes_text' type='NCMText' sub-type='Maintitle'><formatted>[TITRE]this is <uupscommand value='8' type='il'/><uupscommand value='4' type='cj'/>headline1<uupscommand type='cj'/><uupscommand type='il'/><uupscommand type='ep'/>this is line 2[/TITRE]</formatted></content-property></content-property><copy_obj_id type='Integer'>0</copy_obj_id><copy_obj_mode type='Integer'>0</copy_obj_mode><variant_of_obj_id type='Integer'>9859</variant_of_obj_id><variant_type name='PRINT' id='4098'/><numb_of_variants type='Integer'>0</numb_of_variants><relation_obj_id type='Integer'>0</relation_obj_id><sp_id type='Integer'>9857</sp_id><numb_of_sp_objs type='Integer'>0</numb_of_sp_objs><relation_type type='Integer'>0</relation_type><exp_page_number type='Integer'>0</exp_page_number><n_links type='Integer'>0</n_links><template_id type='Integer'>0</template_id><channel name='PRINT' id='1'/><data_type type='String'>NewsRoom</data_type><var_group_last_update type='NCMLastUpdatedVariant'><last-obj-id type='Integer'>9863</last-obj-id><last-obj-name type='String'>TESTJP10-B_PRINT</last-obj-name><last-obj-upd-relevance type='Short'>0</last-obj-upd-relevance><last-content-modifier-ts type='Date'>28.3.2012</last-content-modifier-ts><last-content-modifier type='NCMUser'><id>5</id><name>MARIANOJP</name><type>SYSADMIN</type></last-content-modifier><variant_type name='PRINT' id='4098'/></var_group_last_update><init_obj_mode type='Integer'>0</init_obj_mode><ncm-attachment-property name='attachments' type='NCMAttachment' count='0'/><upd_relevance type='Short'>0</upd_relevance><flags type='Integer'>0</flags><orig_obj_id type='Integer'>0</orig_obj_id><size_graphical_file type='Long'>-1</size_graphical_file><size_native_file type='Long'>-1</size_native_file><property name='copy_infos' type='NCMCopyInfo'>0-0-0-0-0-0</property><mediatype type='String'>ncm-object-2-NewsRoom</mediatype><is_object_link type='Boolean'>false</is_object_link><allowed_pagination type='Boolean'>true</allowed_pagination><extra-properties/><layouts-of-a-ncm-object count='1'><ncm-layout pk='9863:0' classversion='1.0'><dummy_obj_id type='Integer'>9863</dummy_obj_id><edition name='FIRST' id='68' master-edition-name='*****' nm='1ST' zone-name='MAIN' time-name='FIRST'><newspaper-level level-path='NP'><level name='NP' id='3.0.0.0.0' path='NP' level='1' type='Newspaper,AllCatalogs'/></newspaper-level><page-level level-path=''><level name='ROOT' id='0.0.0.0.0' path='' level='0' type='AllCatalogs'/></page-level></edition><is_inpage type='Boolean'>false</is_inpage><obj_id type='Integer'>9863</obj_id><sub_reference type='Integer'>0</sub_reference><jump_sequence type='Integer'>0</jump_sequence><ncm-type-property name='lay_type' type='NCMType' is-external='false' data-type=''><object-type name='OBJ_HEADLINE' id='2' histories='50'><initial-status><status id='9' name='STORY_NEW'/></initial-status></object-type></ncm-type-property><hermes_version type='Integer'>0</hermes_version><newflag type='Integer'>0</newflag><format type='String'>34-2LIGNE</format><surface type='Integer'>2844644</surface><agenda_id type='Integer'>0</agenda_id><assignto type='Integer'>0</assignto><obj_crc type='Integer'>205413666</obj_crc><obj_content type='String'>AAACASYAAAAAAAAAAAAAAAAAAAAAAAAASEkyQgABAQBEAAAAjAAAAAAAAAA=</obj_content><copy_lay_mode type='Integer'>0</copy_lay_mode><init_lay_mode type='Integer'>0</init_lay_mode><version_ts type='Date'>1.1.1970</version_ts><lay_id type='Integer'>0</lay_id><status type='NCMStatus'><status id='9' name='STORY_NEW'/><extended-status type='Integer'>3</extended-status><attribute type='Integer'>3</attribute><complex-status type='Integer'>1</complex-status><sendto type='list'><sendto>0</sendto></sendto></status><ext_status type='String'>3</ext_status><first_linked type='Boolean'>true</first_linked><edition name='*****' id='0'/><page_id type='Integer'>0</page_id><sp_lay_id type='Integer'>0</sp_lay_id><mediatype type='String'>ncm-layout</mediatype><level name='ROOT' id='0.0.0.0.0' path='' level='0' type='AllCatalogs'/><property name='msendto' type='NCMMultipleSendTo'>0</property><real_size type='Integer'>714</real_size><real_lines type='Integer'>2</real_lines><priority type='Short'>0</priority><mandatory type='Short'>0</mandatory><unique_alt_id type='Integer'>0</unique_alt_id><copy_lay_id type='Integer'>0</copy_lay_id><hermes-layout name='lay_rect' type='NCMLayBoundRect' units='PtPs'><bounding-rect xpos='0.0' ypos='207.8' width='380.3' depth='74.8' lay-lines='2'/><hermes-layout-parts><is-dummy-image type='Boolean'>true</is-dummy-image><name-template type='String'>SP</name-template><layout-parts count='1'><layout-box subreference='66' type='2' finfo='0x4012' lock='0x0' exp-name='' style-sheet='Titre'><bounding-boxes count='1'><block parent-id='9857' Units='PtPs' x='0.0' y='207.8' width='380.3' height='74.8'><rotation/><interior-color c='0' m='0' y='0' k='0'/><border-color size='0.0' c='0' m='0' y='0' k='255'/></block></bounding-boxes></layout-box></layout-parts></hermes-layout-parts></hermes-layout><extra-properties/></ncm-layout></layouts-of-a-ncm-object></ncm-object></variants-of-a-ncm-object></ncm-object><ncm-object pk='9860:3724:ALT1' classversion='1.0'><pubnumber type='String'/><obj_id type='Integer'>9860</obj_id><level name='1_CURRENT' id='3.4.1.0.0' path='NP/NEWS/1_CURRENT' level='3' type='Object,HasDate'/><name type='String'>TESTJP10-D</name><unique_name_key type='String'>3.4.1.0.0</unique_name_key><ncm-type-property name='obj_type' type='NCMType' is-external='false' data-type='NewsRoom'><object-type name='OBJ_FOTO' id='6' histories='10'><initial-status><status id='5' name='IMG_NEW'/></initial-status></object-type></ncm-type-property><exp_pubdate type='Date'>27.3.2012</exp_pubdate><exp_pubdate_days type='Integer'>0</exp_pubdate_days><edition name='*****' id='0'/><purge_obj_id type='Integer'>0</purge_obj_id><is_deleted type='Boolean'>false</is_deleted><creator type='NCMUser'><id>5</id><name>MARIANOJP</name><type>SYSADMIN</type></creator><creation_ts type='Date'>28.3.2012</creation_ts><modifier type='NCMUser'><id>5</id><name>MARIANOJP</name><type>SYSADMIN</type></modifier><modifier_ts type='Date'>28.3.2012</modifier_ts><modifier_ws type='Integer'>1138</modifier_ws><modifying type='NCMUser'/><modifying_ws type='Integer'>0</modifying_ws><modifying_app type='Short'>0</modifying_app><is_locked type='Boolean'>false</is_locked><lock_type type='Short'>0</lock_type><hermes_version type='Integer'>0</hermes_version><storage_format type='Integer'>1</storage_format><priority type='Integer'>0</priority><real_chars type='Integer'>0</real_chars><effectivecolors type='NCMColor'><stdcolors type='String'>CMYK</stdcolors><options type='String'>SEPARATION 4PLATES</options></effectivecolors><parent_id type='Integer'>0</parent_id><department_id type='Integer'>1</department_id><last_update_ts type='Date'>28.3.2012</last_update_ts><property name='retention_time' type='Integer'>0</property><version type='Integer'>0</version><content_version type='Integer'>0</content_version><content_modifier type='NCMUser'><id>5</id><name>MARIANOJP</name><type>SYSADMIN</type></content_modifier><content_modifier_ts type='Date'>28.3.2012</content_modifier_ts><content-property name='hermes_image' type='NCMImage' imagetype='TIFF'><file-property name='hermes_image' type='NCMImage'><file-name>OBJ9860_1.JPG</file-name><original-file href='http://H11LNXVM:8080/ncm/dispatcher?auth=U0VTU0lPTklENDE2NTcxMDgyOjQxNjU3MTA4Mg==&amp;url=/ncm/file?file=/hedata/archive/extObj/Photoshop/6/3/4/1/20120327/0/OBJ9860_1.JPG'><server-path>/hedata/archive/extObj/Photoshop/6/3/4/1/20120327/0/OBJ9860_1.JPG</server-path></original-file><medium-preview href='http://H11LNXVM:8080/ncm/dispatcher?auth=U0VTU0lPTklENDE2NTcxMDgyOjQxNjU3MTA4Mg==&amp;url=/ncm/file?file=/hedata/archive/extObj/Photoshop/6/3/4/1/20120327/0/OBJ9860_1.low'><server-path>/hedata/archive/extObj/Photoshop/6/3/4/1/20120327/0/OBJ9860_1.low</server-path></medium-preview><low-preview href='http://H11LNXVM:8080/ncm/dispatcher?auth=U0VTU0lPTklENDE2NTcxMDgyOjQxNjU3MTA4Mg==&amp;url=/ncm/file?file=/hedata/archive/extObj/Photoshop/6/3/4/1/20120327/0/OBJ9860_1.thn'><server-path>/hedata/archive/extObj/Photoshop/6/3/4/1/20120327/0/OBJ9860_1.thn</server-path></low-preview></file-property><image-size type='NCMRect' unit='Pixel'><width>300.0</width><height>300.0</height></image-size><original-image-size type='NCMRect' unit='PSP'><width>288.0</width><height>288.0</height></original-image-size><crop-rect top='0' left='0' bottom='300' right='300'/><img-position llx='0.0' lly='0.0' lrx='288.0' lry='0.0' ulx='0.0' uly='288.0' urx='288.0' ury='288.0'/><xy-transf rotate='0.0' skew='0.0' crop-off-x='0.0' crop-off-y='0.0' norg-x='0.0' norg-y='0.0' scale-x='100.0' scale-y='100.0' dim-x='288.0' dim-y='288.0' flip-x='false' flip-y='false'/><bounding-box top='0.0' left='0.0' bottom='288.0' right='288.0'/></content-property><copy_obj_id type='Integer'>0</copy_obj_id><copy_obj_mode type='Integer'>0</copy_obj_mode><variant_of_obj_id type='Integer'>0</variant_of_obj_id><variant_type name='' id='0'/><numb_of_variants type='Integer'>0</numb_of_variants><relation_obj_id type='Integer'>0</relation_obj_id><sp_id type='Integer'>9857</sp_id><numb_of_sp_objs type='Integer'>0</numb_of_sp_objs><relation_type type='Integer'>0</relation_type><exp_page_number type='Integer'>0</exp_page_number><n_links type='Integer'>1</n_links><template_id type='Integer'>0</template_id><data_type type='String'>NewsRoom</data_type><var_group_last_update type='NCMLastUpdatedVariant'><last-obj-id type='Integer'>9860</last-obj-id><last-obj-name type='String'>TESTJP10-D</last-obj-name><last-obj-upd-relevance type='Short'>0</last-obj-upd-relevance><last-content-modifier-ts type='Date'>28.3.2012</last-content-modifier-ts><last-content-modifier type='NCMUser'><id>5</id><name>MARIANOJP</name><type>SYSADMIN</type></last-content-modifier><variant_type name='' id='0'/></var_group_last_update><init_obj_mode type='Integer'>0</init_obj_mode><ncm-attachment-property name='attachments' type='NCMAttachment' count='0'/><upd_relevance type='Short'>0</upd_relevance><flags type='Integer'>0</flags><orig_obj_id type='Integer'>0</orig_obj_id><size_graphical_file type='Long'>-1</size_graphical_file><size_native_file type='Long'>-1</size_native_file><property name='copy_infos' type='NCMCopyInfo'>0-0-0-0-0-0</property><mediatype type='String'>ncm-object-6-NewsRoom</mediatype><is_object_link type='Boolean'>false</is_object_link><allowed_pagination type='Boolean'>true</allowed_pagination><extra-properties/><layouts-of-a-ncm-object count='1'><ncm-layout pk='9860:3724:ALT1' classversion='1.0'><dummy_obj_id type='Integer'>0</dummy_obj_id><edition name='*****' id='0'/><is_inpage type='Boolean'>true</is_inpage><obj_id type='Integer'>9860</obj_id><reference type='String'>TESTJP10-D</reference><sub_reference type='Integer'>68</sub_reference><jump_sequence type='Integer'>0</jump_sequence><ncm-type-property name='lay_type' type='NCMType' is-external='false' data-type=''><object-type name='OBJ_FOTO' id='6' histories='10'><initial-status><status id='5' name='IMG_NEW'/></initial-status></object-type></ncm-type-property><hermes_version type='Integer'>0</hermes_version><newflag type='Integer'>0</newflag><format type='String'>SP</format><surface type='Integer'>5412022</surface><agenda_id type='Integer'>0</agenda_id><assignto type='Integer'>0</assignto><obj_crc type='Integer'>-619023395</obj_crc><obj_content type='String'>AAAGAP0BAQFAAEALQAvtAQAAAAAAAAolTlJPYmplY3Q6IFRJRkYKJUFMREltYWdlUmVzb2x1dGlv
bjogNzUuMDAwMDAwIDc1LjAwMDAwMAolJUJvdW5kaW5nQm94OiAwIDAgMjg4LjAwMDAwMCAyODgu
MDAwMDAwCiVOUk9yaWdSYXN0ZXJTaXplOiAyODguMDAwMDAwIDI4OC4wMDAwMDAKJU5SRmlsZU5h
bWU6IC9oZWRhdGEvYXJjaGl2ZS9leHRPYmovUGhvdG9zaG9wLzYvMy80LzEvMjAxMjAzMjcvMC9P
Qko5ODYwXzEuSlBHCiVOUkFyY2hpdmU6IAolTlJDbGlwUGF0aEZsYWc6IDAKJU5SSW1hZ2VEaW1l
bnNpb25zOiAzMDAgMzAwCiVOUkltYWdlQ3JvcFJlY3Q6IDAgMCAzMDAgMzAwCiVOUkltYWdlUG9z
aXRpb246IDAgMCAwIDI4OC4wMDAwMDAgMjg4LjAwMDAwMCAyODguMDAwMDAwIDI4OC4wMDAwMDAg
MAolTlJYWVRyYW5zZjogMTAwMDAgMTAwMDAgMCAwIDAgMCAwIDAgMTIwMDAwMCAxMjAwMDAwIDAg
MAolTlJOYXRpdmVBcHA6IFBob3Rvc2hvcAolTlJOYXRpdmVWZXJzOiAxMC4zCiVOUk9iamVjdEVu
ZAo=</obj_content><copy_lay_mode type='Integer'>0</copy_lay_mode><init_lay_mode type='Integer'>0</init_lay_mode><version_ts type='Date'>1.1.1970</version_ts><lay_id type='Integer'>3724</lay_id><status type='NCMStatus'><status id='5' name='IMG_NEW'/><extended-status type='Integer'>0</extended-status><attribute type='Integer'>2</attribute><complex-status type='Integer'>1</complex-status><sendto type='list'><sendto>0</sendto></sendto></status><ext_status type='String'>0</ext_status><first_linked type='Boolean'>true</first_linked><edition name='FIRST' id='68' master-edition-name='*****' nm='1ST' zone-name='MAIN' time-name='FIRST'><newspaper-level level-path='NP'><level name='NP' id='3.0.0.0.0' path='NP' level='1' type='Newspaper,AllCatalogs'/></newspaper-level><page-level level-path=''><level name='ROOT' id='0.0.0.0.0' path='' level='0' type='AllCatalogs'/></page-level></edition><page_id type='Integer'>2452</page_id><sp_lay_id type='Integer'>0</sp_lay_id><page_name type='String'>NPS-003</page_name><mediatype type='String'>ncm-layout</mediatype><pub_date type='Date'>27.3.2012</pub_date><level name='PAGES' id='3.4.3.0.0' path='NP/NEWS/PAGES' level='3' type='Page,HasDate'/><property name='msendto' type='NCMMultipleSendTo'>0</property><real_size type='Integer'>2880</real_size><real_lines type='Integer'>2880</real_lines><priority type='Short'>0</priority><mandatory type='Short'>0</mandatory><unique_alt_id type='Integer'>1</unique_alt_id><copy_lay_id type='Integer'>0</copy_lay_id><hermes-layout name='lay_rect' type='NCMLayBoundRect' units='PtPs'><bounding-rect xpos='130.3' ypos='286.9' width='248.6' depth='226.9' lay-lines='0'/><hermes-layout-parts><is-dummy-image type='Boolean'>false</is-dummy-image><layout-parts count='1'><layout-box subreference='68' type='6' finfo='0x10' lock='0x0' exp-name='' style-sheet=''><bounding-boxes count='1'><block parent-id='9857' Units='PtPs' x='130.3' y='286.9' width='248.6' height='217.7'><rotation/><interior-color c='0' m='0' y='0' k='0'/><border-color size='0.5' c='0' m='0' y='0' k='255'/></block></bounding-boxes></layout-box></layout-parts></hermes-layout-parts></hermes-layout><extra-properties/></ncm-layout></layouts-of-a-ncm-object></ncm-object><ncm-object pk='9863:0' classversion='1.0'><pubnumber type='String'/><obj_id type='Integer'>9863</obj_id><level name='1_CURRENT' id='3.4.1.0.0' path='NP/NEWS/1_CURRENT' level='3' type='Object,HasDate'/><name type='String'>TESTJP10-B_PRINT</name><unique_name_key type='String'>3.4.1.0.0</unique_name_key><ncm-type-property name='obj_type' type='NCMType' is-external='false' data-type='NewsRoom'><object-type name='OBJ_HEADLINE' id='2' histories='50'><initial-status><status id='9' name='STORY_NEW'/></initial-status></object-type></ncm-type-property><exp_pubdate type='Date'>27.3.2012</exp_pubdate><exp_pubdate_days type='Integer'>0</exp_pubdate_days><edition name='FIRST' id='68' master-edition-name='*****' nm='1ST' zone-name='MAIN' time-name='FIRST'><newspaper-level level-path='NP'><level name='NP' id='3.0.0.0.0' path='NP' level='1' type='Newspaper,AllCatalogs'/></newspaper-level><page-level level-path=''><level name='ROOT' id='0.0.0.0.0' path='' level='0' type='AllCatalogs'/></page-level></edition><purge_obj_id type='Integer'>0</purge_obj_id><is_deleted type='Boolean'>false</is_deleted><creator type='NCMUser'><id>5</id><name>MARIANOJP</name><type>SYSADMIN</type></creator><creation_ts type='Date'>28.3.2012</creation_ts><modifier type='NCMUser'><id>5</id><name>MARIANOJP</name><type>SYSADMIN</type></modifier><modifier_ts type='Date'>28.3.2012</modifier_ts><modifier_ws type='Integer'>1138</modifier_ws><modifying type='NCMUser'/><modifying_ws type='Integer'>0</modifying_ws><modifying_app type='Short'>0</modifying_app><is_locked type='Boolean'>false</is_locked><lock_type type='Short'>0</lock_type><hermes_version type='Integer'>0</hermes_version><storage_format type='Integer'>0</storage_format><priority type='Integer'>0</priority><author type='String'>MARIANOJP</author><real_chars type='Integer'>32</real_chars><effectivecolors type='NCMColor'><stdcolors type='String'>K</stdcolors><options type='String'>SEPARATION 4PLATES</options></effectivecolors><text_preview type='String'>this is headline1
this is line  </text_preview><parent_id type='Integer'>0</parent_id><department_id type='Integer'>1</department_id><last_update_ts type='Date'>28.3.2012</last_update_ts><property name='retention_time' type='Integer'>0</property><version type='Integer'>0</version><content_version type='Integer'>0</content_version><content_modifier type='NCMUser'><id>5</id><name>MARIANOJP</name><type>SYSADMIN</type></content_modifier><content_modifier_ts type='Date'>28.3.2012</content_modifier_ts><content-property name='hermes_header' type='NCMHeader'><content-property name='hermes_image' type='NCMImage' imagetype='TIFF'><file-property name='hermes_image' type='NCMImage'><file-name>OBJ9863_5.JPG</file-name><original-file href='http://H11LNXVM:8080/ncm/dispatcher?auth=U0VTU0lPTklENDE2NTcxMDgyOjQxNjU3MTA4Mg==&amp;url=/ncm/file?file=/hedata/archive/extObj/NewsRoom/2/3/4/1/20120327/68/OBJ9863_5.JPG'><server-path>/hedata/archive/extObj/NewsRoom/2/3/4/1/20120327/68/OBJ9863_5.JPG</server-path></original-file><medium-preview href='http://H11LNXVM:8080/ncm/dispatcher?auth=U0VTU0lPTklENDE2NTcxMDgyOjQxNjU3MTA4Mg==&amp;url=/ncm/file?file=/hedata/archive/extObj/NewsRoom/2/3/4/1/20120327/68/OBJ9863_5.low'><server-path>/hedata/archive/extObj/NewsRoom/2/3/4/1/20120327/68/OBJ9863_5.low</server-path></medium-preview><low-preview href='http://H11LNXVM:8080/ncm/dispatcher?auth=U0VTU0lPTklENDE2NTcxMDgyOjQxNjU3MTA4Mg==&amp;url=/ncm/file?file=/hedata/archive/extObj/NewsRoom/2/3/4/1/20120327/68/OBJ9863_5.thn'><server-path>/hedata/archive/extObj/NewsRoom/2/3/4/1/20120327/68/OBJ9863_5.thn</server-path></low-preview></file-property><image-size type='NCMRect' unit='Pixel'><width>0.0</width><height>0.0</height></image-size><original-image-size type='NCMRect' unit='PSP'><width>0.0</width><height>0.0</height></original-image-size><xy-transf rotate='0.0' skew='0.0' crop-off-x='0.0' crop-off-y='0.0' norg-x='0.0' norg-y='0.0' scale-x='100.0' scale-y='100.0' dim-x='380.0' dim-y='74.0' flip-x='false' flip-y='false'/><bounding-box top='0.0' left='0.0' bottom='0.0' right='380.0'/></content-property><content-property name='hermes_text' type='NCMText' sub-type='Maintitle'><formatted>[TITRE]this is <uupscommand value='8' type='il'/><uupscommand value='4' type='cj'/>headline1<uupscommand type='cj'/><uupscommand type='il'/><uupscommand type='ep'/>this is line 2[/TITRE]</formatted></content-property></content-property><copy_obj_id type='Integer'>0</copy_obj_id><copy_obj_mode type='Integer'>0</copy_obj_mode><variant_of_obj_id type='Integer'>9859</variant_of_obj_id><variant_type name='PRINT' id='4098'/><numb_of_variants type='Integer'>0</numb_of_variants><relation_obj_id type='Integer'>0</relation_obj_id><sp_id type='Integer'>9857</sp_id><numb_of_sp_objs type='Integer'>0</numb_of_sp_objs><relation_type type='Integer'>0</relation_type><exp_page_number type='Integer'>0</exp_page_number><n_links type='Integer'>0</n_links><template_id type='Integer'>0</template_id><channel name='PRINT' id='1'/><data_type type='String'>NewsRoom</data_type><var_group_last_update type='NCMLastUpdatedVariant'><last-obj-id type='Integer'>9863</last-obj-id><last-obj-name type='String'>TESTJP10-B_PRINT</last-obj-name><last-obj-upd-relevance type='Short'>0</last-obj-upd-relevance><last-content-modifier-ts type='Date'>28.3.2012</last-content-modifier-ts><last-content-modifier type='NCMUser'><id>5</id><name>MARIANOJP</name><type>SYSADMIN</type></last-content-modifier><variant_type name='PRINT' id='4098'/></var_group_last_update><init_obj_mode type='Integer'>0</init_obj_mode><ncm-attachment-property name='attachments' type='NCMAttachment' count='0'/><upd_relevance type='Short'>0</upd_relevance><flags type='Integer'>0</flags><orig_obj_id type='Integer'>0</orig_obj_id><size_graphical_file type='Long'>-1</size_graphical_file><size_native_file type='Long'>-1</size_native_file><property name='copy_infos' type='NCMCopyInfo'>0-0-0-0-0-0</property><mediatype type='String'>ncm-object-2-NewsRoom</mediatype><is_object_link type='Boolean'>false</is_object_link><allowed_pagination type='Boolean'>true</allowed_pagination><extra-properties/><layouts-of-a-ncm-object count='1'><ncm-layout pk='9863:0' classversion='1.0'><dummy_obj_id type='Integer'>9863</dummy_obj_id><edition name='FIRST' id='68' master-edition-name='*****' nm='1ST' zone-name='MAIN' time-name='FIRST'><newspaper-level level-path='NP'><level name='NP' id='3.0.0.0.0' path='NP' level='1' type='Newspaper,AllCatalogs'/></newspaper-level><page-level level-path=''><level name='ROOT' id='0.0.0.0.0' path='' level='0' type='AllCatalogs'/></page-level></edition><is_inpage type='Boolean'>false</is_inpage><obj_id type='Integer'>9863</obj_id><sub_reference type='Integer'>0</sub_reference><jump_sequence type='Integer'>0</jump_sequence><ncm-type-property name='lay_type' type='NCMType' is-external='false' data-type=''><object-type name='OBJ_HEADLINE' id='2' histories='50'><initial-status><status id='9' name='STORY_NEW'/></initial-status></object-type></ncm-type-property><hermes_version type='Integer'>0</hermes_version><newflag type='Integer'>0</newflag><format type='String'>34-2LIGNE</format><surface type='Integer'>2844644</surface><agenda_id type='Integer'>0</agenda_id><assignto type='Integer'>0</assignto><obj_crc type='Integer'>205413666</obj_crc><obj_content type='String'>AAACASYAAAAAAAAAAAAAAAAAAAAAAAAASEkyQgABAQBEAAAAjAAAAAAAAAA=</obj_content><copy_lay_mode type='Integer'>0</copy_lay_mode><init_lay_mode type='Integer'>0</init_lay_mode><version_ts type='Date'>1.1.1970</version_ts><lay_id type='Integer'>0</lay_id><status type='NCMStatus'><status id='9' name='STORY_NEW'/><extended-status type='Integer'>3</extended-status><attribute type='Integer'>3</attribute><complex-status type='Integer'>1</complex-status><sendto type='list'><sendto>0</sendto></sendto></status><ext_status type='String'>3</ext_status><first_linked type='Boolean'>true</first_linked><edition name='*****' id='0'/><page_id type='Integer'>0</page_id><sp_lay_id type='Integer'>0</sp_lay_id><mediatype type='String'>ncm-layout</mediatype><level name='ROOT' id='0.0.0.0.0' path='' level='0' type='AllCatalogs'/><property name='msendto' type='NCMMultipleSendTo'>0</property><real_size type='Integer'>714</real_size><real_lines type='Integer'>2</real_lines><priority type='Short'>0</priority><mandatory type='Short'>0</mandatory><unique_alt_id type='Integer'>0</unique_alt_id><copy_lay_id type='Integer'>0</copy_lay_id><hermes-layout name='lay_rect' type='NCMLayBoundRect' units='PtPs'><bounding-rect xpos='0.0' ypos='207.8' width='380.3' depth='74.8' lay-lines='2'/><hermes-layout-parts><is-dummy-image type='Boolean'>true</is-dummy-image><name-template type='String'>SP</name-template><layout-parts count='1'><layout-box subreference='66' type='2' finfo='0x4012' lock='0x0' exp-name='' style-sheet='Titre'><bounding-boxes count='1'><block parent-id='9857' Units='PtPs' x='0.0' y='207.8' width='380.3' height='74.8'><rotation/><interior-color c='0' m='0' y='0' k='0'/><border-color size='0.0' c='0' m='0' y='0' k='255'/></block></bounding-boxes></layout-box></layout-parts></hermes-layout-parts></hermes-layout><extra-properties/></ncm-layout></layouts-of-a-ncm-object></ncm-object></child-of-a-ncm-sp-object><layouts-of-a-ncm-object count='1'><ncm-layout pk='9857:3725:ALT1' classversion='1.0'><dummy_obj_id type='Integer'>0</dummy_obj_id><edition name='*****' id='0'/><is_inpage type='Boolean'>true</is_inpage><obj_id type='Integer'>9857</obj_id><reference type='String'>A</reference><sub_reference type='Integer'>0</sub_reference><jump_sequence type='Integer'>0</jump_sequence><ncm-type-property name='lay_type' type='NCMType' is-external='false' data-type=''><object-type name='OBJ_STORY_PACK' id='17' histories='0'><initial-status><status id='52' name='SP'/></initial-status></object-type></ncm-type-property><hermes_version type='Integer'>0</hermes_version><newflag type='Integer'>0</newflag><format type='String'>SP</format><surface type='Integer'>0</surface><agenda_id type='Integer'>0</agenda_id><assignto type='Integer'>0</assignto><obj_crc type='Integer'>0</obj_crc><obj_content type='String'/><copy_lay_mode type='Integer'>0</copy_lay_mode><init_lay_mode type='Integer'>0</init_lay_mode><version_ts type='Date'>1.1.1970</version_ts><lay_id type='Integer'>3725</lay_id><status type='NCMStatus'><status id='52' name='SP'/><extended-status type='Integer'>2</extended-status><attribute type='Integer'>4</attribute><complex-status type='Integer'>1</complex-status><sendto type='list'><sendto>0</sendto></sendto></status><ext_status type='String'>2</ext_status><first_linked type='Boolean'>true</first_linked><edition name='FIRST' id='68' master-edition-name='*****' nm='1ST' zone-name='MAIN' time-name='FIRST'><newspaper-level level-path='NP'><level name='NP' id='3.0.0.0.0' path='NP' level='1' type='Newspaper,AllCatalogs'/></newspaper-level><page-level level-path=''><level name='ROOT' id='0.0.0.0.0' path='' level='0' type='AllCatalogs'/></page-level></edition><page_id type='Integer'>2452</page_id><sp_lay_id type='Integer'>3725</sp_lay_id><page_name type='String'>NPS-003</page_name><mediatype type='String'>ncm-layout</mediatype><pub_date type='Date'>27.3.2012</pub_date><level name='PAGES' id='3.4.3.0.0' path='NP/NEWS/PAGES' level='3' type='Page,HasDate'/><property name='msendto' type='NCMMultipleSendTo'>0</property><real_size type='Integer'>0</real_size><real_lines type='Integer'>50</real_lines><priority type='Short'>0</priority><mandatory type='Short'>0</mandatory><unique_alt_id type='Integer'>1</unique_alt_id><copy_lay_id type='Integer'>0</copy_lay_id><hermes-layout name='lay_rect' type='NCMLayBoundRect' units='PtPs'><bounding-rect xpos='0.0' ypos='207.8' width='380.3' depth='377.6' lay-lines='0'/><hermes-layout-parts><is-dummy-image type='Boolean'>false</is-dummy-image><layout-parts count='0'/></hermes-layout-parts></hermes-layout><extra-properties/></ncm-layout></layouts-of-a-ncm-object></ncm-object>